LICENSE
README.md
setup.py
icode123/__init__.py
icode123.egg-info/PKG-INFO
icode123.egg-info/SOURCES.txt
icode123.egg-info/dependency_links.txt
icode123.egg-info/entry_points.txt
icode123.egg-info/requires.txt
icode123.egg-info/top_level.txt