Metadata-Version: 2.1
Name: icode123
Version: 0.0.3
Summary: 一个本地开发环境检测库。
Home-page: https://github.com/xuehang00126/icode123
Author: 学航
Author-email: xuehang00126@126.com
License: MIT License
Keywords: check
Platform: any
License-File: LICENSE
